{
    "window": [5, 3],
    "symbols":
    [
        {
            "name": "Scatter",
            "payment": [],
            "direction": "any",
            "base":
            {
              "scatter": [[3, 10], [4, 15], [5, 20]]
            }
        },
        {
            "name": "Wild",
            "payment": [[5, 500]],
            "base":
            {
              "wild":
              {
              }
            }
        },
        {
            "name": "S1",
            "payment": [[3, 30], [4, 90], [5, 300]]
        },
        {
            "name": "S2",
            "payment": [[3, 17], [4, 60], [5, 170]]
        },
        {
            "name": "j1",
            "payment": [[3, 12], [4, 35], [5, 120]]
        },
        {
            "name": "j2",
            "payment": [[3, 10], [4, 30], [5, 100]]
        },
        {
            "name": "j3",
            "payment": [[3, 6], [4, 20], [5, 60]]
        },
        {
            "name": "j4",
            "payment": [[3, 5], [4, 15], [5, 50]]
        },
        {
            "name": "j5",
            "payment": [[3, 4], [4, 12], [5, 40]]
        },
        {
            "name": "j6",
            "payment": [[3, 3], [4, 10], [5, 30]]
        }
    ],
    "lines":
    [
        [2,2,2,2,2],
        [1,1,1,1,1],
        [3,3,3,3,3],
        [1,2,3,2,1],
        [3,2,1,2,3],
        [1,1,2,3,3],
        [3,3,2,1,1],
        [2,3,3,3,2],
        [2,1,1,1,2],
        [1,2,2,2,1]
    ],
    "RTP": [-1, 1],
    "baseRTP": [0.65, 0.01],
    "volatility": [12, 20],
    "hitrate": [140, 1]
}